{
  "id": 1004,
  "name": "Apple Inc.",
  "short_name": "Apple",
  "hiring_velocity": "High",
  "profitability_status": "Break-even",
  "remote_policy_details": "Hybrid",
  "logo_url": "https://logo.clearbit.com/apple.com",
  "full_json": "/data/Companies_Full/4_Apple_Inc_.json",
  "hiring_json": "/data/Hiring_Grounds/4_Apple_Inc_.json",
  "innovx_json": "/data/InnoVex/4_Apple_Inc_.json",
  "incorporation_year": 1984,
  "nature_of_company": "Public",
  "headquarters_address": "Global HQ",
  "operating_countries": "Global",
  "office_count": 54,
  "office_locations": "Bangalore, India; New York, USA; London, UK",
  "employee_size": "30,000 employees",
  "overview_text": "Apple Inc. is a global leader in the Go ecosystem.",
  "pain_points_addressed": "Digital transformation and scalability.",
  "focus_sectors": "Technology, Finance, Healthcare",
  "tech_stack": "Go, Kubernetes, TypeScript",
  "annual_revenue": "$5 Billion+",
  "yoy_growth_rate": "15%",
  "primary_contact_email": "contact@apple.com"
}