{
  "id": 1074,
  "name": "Autodesk",
  "short_name": "Autodesk",
  "hiring_velocity": "Low",
  "profitability_status": "Loss-making",
  "remote_policy_details": "On-site",
  "logo_url": "https://logo.clearbit.com/autodesk.com",
  "full_json": "/data/Companies_Full/74_Autodesk.json",
  "hiring_json": "/data/Hiring_Grounds/74_Autodesk.json",
  "innovx_json": "/data/InnoVex/74_Autodesk.json",
  "incorporation_year": 2014,
  "nature_of_company": "Public",
  "headquarters_address": "Global HQ",
  "operating_countries": "Global",
  "office_count": 124,
  "office_locations": "Bangalore, India; New York, USA; London, UK",
  "employee_size": "380,000 employees",
  "overview_text": "Autodesk is a global leader in the Docker ecosystem.",
  "pain_points_addressed": "Digital transformation and scalability.",
  "focus_sectors": "Technology, Finance, Healthcare",
  "tech_stack": "Docker, PyTorch, Next.js",
  "annual_revenue": "$75 Billion+",
  "yoy_growth_rate": "15%",
  "primary_contact_email": "contact@autodesk.com"
}